{
    "text": "1942年3月24日讯：日政府将厦门与鼓浪屿“移交”汪伪政府管理，伪行政院秘书 陈春圃赴厦门“接收”。（25 日，陈又赴广州“接收”沙面英租界。该租界 今后将划为广东省政府特别行政区，由广州特别区公处管理，处长由广 东省警察局长郭卫氏兼任。日派遣军酒井最高指挥官发表声明: ... ",
    "user_id": 2896390104,
    "screen_name": "抗战直播",
    "id": 4088953059641022,
    "bid": "EBk4FEs4m",
    "article_url": "",
    "pics": "https://wx4.sinaimg.cn/large/aca367d8ly1fdyavtj1gpj20c80aywel.jpg",
    "video_url": "",
    "location": "",
    "created_at": "2017-03-24",
    "source": "皮皮时光机",
    "attitudes_count": 3,
    "comments_count": 0,
    "reposts_count": 3,
    "topics": "",
    "at_users": "",
    "history_date": "1942年03月24日",
    "type": 0
}