{
    "text": "#远征军第一次入缅作战#1942年5月10日讯：日军第56师团主力进至八莫后，派出一部兵力向西进攻，企图切断曼德勒至密支那的铁路，在杰沙遭到第113团的阻击，战况激烈，我军终于遏止了日军的攻势。但归国的路线已被切断，只能从曼密铁路以西地区向孟关、打洛之线转进。 ",
    "user_id": 2896390104,
    "screen_name": "抗战直播",
    "id": 4105766338534539,
    "bid": "F2q0xzOdR",
    "article_url": "",
    "pics": "",
    "video_url": "",
    "location": "",
    "created_at": "2017-05-10",
    "source": "皮皮时光机",
    "attitudes_count": 5,
    "comments_count": 0,
    "reposts_count": 2,
    "topics": "远征军第一次入缅作战",
    "at_users": "",
    "history_date": "1942年05月10日",
    "type": 0
}