{
    "text": "1938年8月28日讯：沙河敌军南犯受挫，敌猛攻南浔正面并狂炸德安城，星子南牛尾墩各处阵地已克复 ",
    "user_id": 2896390104,
    "screen_name": "抗战直播",
    "id": 3616240616998644,
    "bid": "A6OuxtmFm",
    "article_url": "",
    "pics": "https://ww3.sinaimg.cn/large/aca367d8jw1e828lxeak4j20c116c77y.jpg",
    "video_url": "",
    "location": "",
    "created_at": "2013-08-28",
    "source": "皮皮时光机",
    "attitudes_count": 0,
    "comments_count": 0,
    "reposts_count": 0,
    "topics": "",
    "at_users": "",
    "history_date": "1938年08月28日",
    "type": 0
}