{
    "text": "1938年3月12日讯：豫北我游击奏功，敌据点迭被破袭 ",
    "user_id": 2896390104,
    "screen_name": "抗战直播",
    "id": 3554966898087317,
    "bid": "zn3WhxVSB",
    "article_url": "",
    "pics": "https://ww1.sinaimg.cn/large/aca367d8jw1e2mrf46c2ij.jpg",
    "video_url": "",
    "location": "",
    "created_at": "2013-03-12",
    "source": "皮皮时光机",
    "attitudes_count": 0,
    "comments_count": 0,
    "reposts_count": 0,
    "topics": "",
    "at_users": "",
    "history_date": "1938年03月12日",
    "type": 0
}