{
    "text": "1943年2月11日讯：中央赈济委员会专员赵则诚视察豫、皖灾情，自立煌抵漯河，在漯河发表谈话称：所经界首、周口、漯河等处，老弱饿毙，婴孩被弃，确为目见事实，已将情况电呈中央，并建议豫、皖当局，第一步扩大收容灾童，第二步移民去皖北就食。 ",
    "user_id": 2896390104,
    "screen_name": "抗战直播",
    "id": 4206193075763475,
    "bid": "G2B6Poblh",
    "article_url": "",
    "pics": "",
    "video_url": "",
    "location": "",
    "created_at": "2018-02-11",
    "source": "皮皮时光机",
    "attitudes_count": 2,
    "comments_count": 0,
    "reposts_count": 1,
    "topics": "",
    "at_users": "",
    "history_date": "1943年02月11日",
    "type": 0
}