{
    "text": "1942年8月30日讯：川省建设厅长胡子昂谈川省建设动态:机械制造厂由原省立 机器厂合并，资本1500万元，钱新之任董事长;水泥公司资本700万 元，主办人徐宗涑;农业公司资本600万元，主办人刘伯量;丝亚公司资 本3000万元，张群兼董事长。 ",
    "user_id": 2896390104,
    "screen_name": "抗战直播",
    "id": 4146535061222344,
    "bid": "FjwAy57Ze",
    "article_url": "",
    "pics": "",
    "video_url": "",
    "location": "",
    "created_at": "2017-08-30",
    "source": "皮皮时光机",
    "attitudes_count": 2,
    "comments_count": 0,
    "reposts_count": 1,
    "topics": "",
    "at_users": "",
    "history_date": "1942年08月30日",
    "type": 0
}