{
    "text": "1945年4月27日讯：日军3000余人窜入湖南新化县洋溪，烧杀抢掠，无所不为，共杀害民众3461人，强奸妇女227人，烧毁房屋2.8万余间，毁粮食126.3万余斤，抓走民夫2056人。 ",
    "user_id": 2896390104,
    "screen_name": "抗战直播",
    "id": 4498413838509650,
    "bid": "IFibZzHKq",
    "article_url": "",
    "pics": "",
    "video_url": "",
    "location": "",
    "created_at": "2020-04-27",
    "source": "皮皮时光机",
    "attitudes_count": 5,
    "comments_count": 4,
    "reposts_count": 2,
    "topics": "",
    "at_users": "",
    "history_date": "1945年04月27日",
    "type": 0
}