{
    "text": "1940年6月17日：从欧战中认识一个真理—发展我们的国力 ",
    "user_id": 2896390104,
    "screen_name": "抗战直播",
    "id": 3854624077624235,
    "bid": "CmV1lvZpx",
    "article_url": "",
    "pics": "https://ww4.sinaimg.cn/large/aca367d8jw1et6qklew4zj211y0hd0z2.jpg",
    "video_url": "",
    "location": "",
    "created_at": "2015-06-17",
    "source": "皮皮时光机",
    "attitudes_count": 2,
    "comments_count": 0,
    "reposts_count": 2,
    "topics": "",
    "at_users": "",
    "history_date": "1940年06月17日",
    "type": 0
}