{
    "text": "1945年8月23日讯：苏浙军区解放浙西安吉县城，苏中军区解放宝应县城，歼伪军2000余人。第7师第19旅攻克皖中雍家镇，全歼伪军900余人。淮北军区解放五河县城，俘伪军500余人。 ",
    "user_id": 2896390104,
    "screen_name": "抗战直播",
    "id": 4541069733403890,
    "bid": "Jhepvehvs",
    "article_url": "",
    "pics": "",
    "video_url": "",
    "location": "",
    "created_at": "2020-08-23",
    "source": "皮皮时光机",
    "attitudes_count": 256,
    "comments_count": 17,
    "reposts_count": 12,
    "topics": "",
    "at_users": "",
    "history_date": "1945年08月23日",
    "type": 0
}