{
    "text": "1942年3月15日讯：美国陆军部根据3月8日英美联合参谋会议决定指示史迪 威:英国韦维尔是印度最高统帅，英美联合参谋会议已授权给韦维尔指 挥缅甸战事，任何在印、缅的军队自应受其节制。 ",
    "user_id": 2896390104,
    "screen_name": "抗战直播",
    "id": 4085563226955980,
    "bid": "EzTTctbze",
    "article_url": "",
    "pics": "",
    "video_url": "",
    "location": "",
    "created_at": "2017-03-15",
    "source": "皮皮时光机",
    "attitudes_count": 1,
    "comments_count": 0,
    "reposts_count": 1,
    "topics": "",
    "at_users": "",
    "history_date": "1942年03月15日",
    "type": 0
}