{
    "text": "1941年3月11日申报广告 ",
    "user_id": 2896390104,
    "screen_name": "抗战直播",
    "id": 3951977954388945,
    "bid": "DlObpipLr",
    "article_url": "",
    "pics": "https://ww1.sinaimg.cn/large/aca367d8jw1f1tbid1i74j20a60h4wgm.jpg",
    "video_url": "",
    "location": "",
    "created_at": "2016-03-11",
    "source": "皮皮时光机",
    "attitudes_count": 9,
    "comments_count": 0,
    "reposts_count": 3,
    "topics": "",
    "at_users": "",
    "history_date": "1941年03月11日",
    "type": 0
}