{
    "text": "1942年1月19日讯：延安《解放日报》-日军自“七七”抗战后，即实行文化掠夺， 开始成立“华中图书文献接收委员会”，后改名为“华中建设资料整备委 员会”。该会仅在南京、上海、杭州等地即掠夺图书90余万册，地质矿 物标本近五万件，鸟类标本4000余只。 ",
    "user_id": 2896390104,
    "screen_name": "抗战直播",
    "id": 4065601633325141,
    "bid": "ErwB5dX1j",
    "article_url": "",
    "pics": "",
    "video_url": "",
    "location": "",
    "created_at": "2017-01-19",
    "source": "皮皮时光机",
    "attitudes_count": 4,
    "comments_count": 0,
    "reposts_count": 1,
    "topics": "",
    "at_users": "",
    "history_date": "1942年01月19日",
    "type": 0
}