{
    "text": "1940年10月10日讯：外交协会赠送贝当纸伞一柄，暗讽法国对日妥协 ",
    "user_id": 2896390104,
    "screen_name": "抗战直播",
    "id": 3896537669612773,
    "bid": "CEvnUEkIJ",
    "article_url": "",
    "pics": "https://ww3.sinaimg.cn/large/aca367d8jw1ewwga4cnwzj20cp0awjt2.jpg",
    "video_url": "",
    "location": "",
    "created_at": "2015-10-10",
    "source": "皮皮时光机",
    "attitudes_count": 3,
    "comments_count": 0,
    "reposts_count": 1,
    "topics": "",
    "at_users": "",
    "history_date": "1940年10月10日",
    "type": 0
}