{
    "text": "1941年1月24日讯：新春中的国际动态 ",
    "user_id": 2896390104,
    "screen_name": "抗战直播",
    "id": 3934953341067938,
    "bid": "DeFim4tOO",
    "article_url": "",
    "pics": "https://ww4.sinaimg.cn/large/aca367d8jw1f0b09dcrlqj20py0xswzk.jpg",
    "video_url": "",
    "location": "",
    "created_at": "2016-01-24",
    "source": "皮皮时光机",
    "attitudes_count": 5,
    "comments_count": 0,
    "reposts_count": 3,
    "topics": "",
    "at_users": "",
    "history_date": "1941年01月24日",
    "type": 0
}