{
    "text": "直播评论：若日军娘子关、井陉大站以中队200人计，其他小站据点以小队40人计，独立据点以分队13人计，据点遭围攻拔除，战死者多，逃亡者少，粗略推断，晋察冀军区6战即毙伤日军500余人左右，129师11战应毙伤日军千余人以上，120师4战应毙伤敌600余人，其他小的战斗，伪军尚未计算在内。 ",
    "user_id": 2896390104,
    "screen_name": "抗战直播",
    "id": 3885457010522544,
    "bid": "CzR7T2bW8",
    "article_url": "",
    "pics": "",
    "video_url": "",
    "location": "",
    "created_at": "2015-09-10",
    "source": "皮皮时光机",
    "attitudes_count": 2,
    "comments_count": 0,
    "reposts_count": 1,
    "topics": "",
    "at_users": "",
    "history_date": "1940年09月10日",
    "type": 0
}