{
    "text": "1941年10月26日讯：路透社-传苏联远东军参谋官员多被调回欧洲战场 ",
    "user_id": 2896390104,
    "screen_name": "抗战直播",
    "id": 4034889336582968,
    "bid": "EeDD7rCwU",
    "article_url": "",
    "pics": "https://ww4.sinaimg.cn/large/aca367d8jw1f95tr1bnq2j206d061gm3.jpg",
    "video_url": "",
    "location": "",
    "created_at": "2016-10-26",
    "source": "皮皮时光机",
    "attitudes_count": 4,
    "comments_count": 0,
    "reposts_count": 1,
    "topics": "",
    "at_users": "",
    "history_date": "1941年10月26日",
    "type": 0
}