{
    "text": "#参战装备#日本“千岁”号航空母舰，1943年8月该舰改建完工，从水上飞机母舰变为航空母舰，外观上与祥凤级和龙凤级航母相似。满载排水量13600吨，航速29节，舰员785人，武备127毫米双联高炮4座，25毫米三联高炮10座，可搭载零式舰战21架，九七舰攻9架。该舰于1944 年10月恩加诺角海战中被美机炸沉。  ",
    "user_id": 2896390104,
    "screen_name": "抗战直播",
    "id": 3649187687856635,
    "bid": "AkDAYwXRV",
    "article_url": "",
    "pics": "https://ww1.sinaimg.cn/large/aca367d8jw1eazcj0wccnj20m70cy3zv.jpg",
    "video_url": "",
    "location": "",
    "created_at": "2013-11-27",
    "source": "皮皮时光机",
    "attitudes_count": 1,
    "comments_count": 0,
    "reposts_count": 3,
    "topics": "参战装备",
    "at_users": "",
    "history_date": "1938年11月27日",
    "type": 0
}