{
    "text": "#太岳区1943年秋季反扫荡作战# 1943年10月1日讯：太岳军区部队于临(汾)屯(留)公路两则，开始抗击日军第62师团、69师团、37师团的16个大队及伪军共2万余人的“铁滚式扫荡”。 ",
    "user_id": 2896390104,
    "screen_name": "抗战直播",
    "id": 4290267198873596,
    "bid": "GBSgfBeqw",
    "article_url": "",
    "pics": "",
    "video_url": "",
    "location": "",
    "created_at": "2018-10-01",
    "source": "皮皮时光机",
    "attitudes_count": 1,
    "comments_count": 0,
    "reposts_count": 1,
    "topics": "太岳区1943年秋季反扫荡作战",
    "at_users": "",
    "history_date": "1943年10月01日",
    "type": 0
}