{
    "text": "1938年9月3日南洋香烟广告 ",
    "user_id": 2896390104,
    "screen_name": "抗战直播",
    "id": 3618342768443907,
    "bid": "A7Hb6zqE3",
    "article_url": "",
    "pics": "https://ww2.sinaimg.cn/large/aca367d8jw1e88y1db7x0j20fr0iiabd.jpg",
    "video_url": "",
    "location": "",
    "created_at": "2013-09-03",
    "source": "皮皮时光机",
    "attitudes_count": 1,
    "comments_count": 0,
    "reposts_count": 1,
    "topics": "",
    "at_users": "",
    "history_date": "1938年09月03日",
    "type": 0
}