{
    "text": "1939年6月25日讯：综合各方消息，在日方煽动下，华北各地反英运动正持续蔓延，日方并努力使白俄参与其间，在天津的英国人一再遭到日军侮辱 ",
    "user_id": 2896390104,
    "screen_name": "抗战直播",
    "id": 3725455515516679,
    "bid": "BaGdhn98H",
    "article_url": "",
    "pics": "https://ww2.sinaimg.cn/large/aca367d8jw1ehqnrm79cpj204j1spwlp.jpg",
    "video_url": "",
    "location": "",
    "created_at": "2014-06-25",
    "source": "皮皮时光机",
    "attitudes_count": 2,
    "comments_count": 2,
    "reposts_count": 1,
    "topics": "",
    "at_users": "",
    "history_date": "1939年06月25日",
    "type": 0
}