{
    "text": "1944年6月17日讯：国家总动员会议为充实四川省经检力量，加强经检机构，将原有重庆、成都、自贡三个经检队及宜宾、万县经检支队改为第一、二、三、四、五大队，并将全川划为五个经检区。 ",
    "user_id": 2896390104,
    "screen_name": "抗战直播",
    "id": 4384144265609338,
    "bid": "HziYynxfc",
    "article_url": "",
    "pics": "",
    "video_url": "",
    "location": "",
    "created_at": "2019-06-17",
    "source": "皮皮时光机",
    "attitudes_count": 3,
    "comments_count": 0,
    "reposts_count": 0,
    "topics": "",
    "at_users": "",
    "history_date": "1944年06月17日",
    "type": 0
}