{
    "text": "#陈庄战斗#1939年9月25日讯：日军由灵寿进犯慈峪镇，以强火力袭击了我晋察冀4分区独立第5团两个连的警戒阵地，至晚7时，敌即占慈峪镇，并继续向南伍河、北霍营我719团阵地进攻，我军随即节节阻击，将敌诱至南谭庄、北伍河地区。 ",
    "user_id": 2896390104,
    "screen_name": "抗战直播",
    "id": 3758613837659850,
    "bid": "BoAOrw8FY",
    "article_url": "",
    "pics": "",
    "video_url": "",
    "location": "",
    "created_at": "2014-09-25",
    "source": "皮皮时光机",
    "attitudes_count": 1,
    "comments_count": 2,
    "reposts_count": 2,
    "topics": "陈庄战斗",
    "at_users": "",
    "history_date": "1939年09月25日",
    "type": 0
}