{
    "text": "1942年2月1日讯：经济部物资局成立，下设农本局、燃料管理处和平价购 销处。从6月份开始办理煤、油、布等定量分售业务。财政部拨平价基 金4. 5亿元，用以控制生产。 ",
    "user_id": 2896390104,
    "screen_name": "抗战直播",
    "id": 4070252428130774,
    "bid": "EttAmy7bw",
    "article_url": "",
    "pics": "",
    "video_url": "",
    "location": "",
    "created_at": "2017-02-01",
    "source": "皮皮时光机",
    "attitudes_count": 3,
    "comments_count": 0,
    "reposts_count": 1,
    "topics": "",
    "at_users": "",
    "history_date": "1942年02月01日",
    "type": 0
}