{
    "text": "#广西反攻作战#1945年6月15日讯：中国陆军总司令何应钦判断日军无死守柳州之可能，电令第29军和第46军一部会攻柳州；第27集团军向桂林附近推进，准备收复桂林。 ",
    "user_id": 2896390104,
    "screen_name": "抗战直播",
    "id": 4515989628685544,
    "bid": "J6HXIArvq",
    "article_url": "",
    "pics": "",
    "video_url": "",
    "location": "",
    "created_at": "2020-06-15",
    "source": "皮皮时光机",
    "attitudes_count": 8,
    "comments_count": 0,
    "reposts_count": 0,
    "topics": "广西反攻作战",
    "at_users": "",
    "history_date": "1945年06月15日",
    "type": 0
}