{
    "text": "1938年2月16日讯：第129师386旅771团于昔(阳)平(定)公路之凤凰山伏击日军，毙伤敌100余人，并割断交通。#陈赓日记#在17日中记载：接王、徐电，昔阳敌人约三四百人，炮五门，向我771团攻击，我前进部队之一连佯败，将敌诱至凤凰山我军埋伏地，给敌以突然火力袭击，敌死伤百人以上，连夜弃尸逃回城内。 ",
    "user_id": 2896390104,
    "screen_name": "抗战直播",
    "id": 3546284671973714,
    "bid": "zjq4H8hs6",
    "article_url": "",
    "pics": "",
    "video_url": "",
    "location": "",
    "created_at": "2013-02-16",
    "source": "皮皮时光机",
    "attitudes_count": 0,
    "comments_count": 14,
    "reposts_count": 3,
    "topics": "陈赓日记",
    "at_users": "",
    "history_date": "1938年02月16日",
    "type": 0
}