{
    "text": "1940年11月8日讯：东北抗日联军第三路军第十二支队徐泽民部，联合当 地义勇军、爱国士绅，攻克黑龙江肇源县城，将伪军全部缴械，击毙日军 警务长以下日伪军九人，俘虏伪警察116人。 ",
    "user_id": 2896390104,
    "screen_name": "抗战直播",
    "id": 3906802846054813,
    "bid": "D2QYkpp8h",
    "article_url": "",
    "pics": "",
    "video_url": "",
    "location": "",
    "created_at": "2015-11-08",
    "source": "皮皮时光机",
    "attitudes_count": 9,
    "comments_count": 0,
    "reposts_count": 4,
    "topics": "",
    "at_users": "",
    "history_date": "1940年11月08日",
    "type": 0
}