{
    "text": "1942年12月18日讯：中共中央北方局代理书记、八路军副总司令彭德怀在太行军 区干部会议上批评华北各地对地方武装忽视和吞并的行为，指出这是 把游击战估计过低，把运动战估计过高所犯的错误。 ",
    "user_id": 2896390104,
    "screen_name": "抗战直播",
    "id": 4186276955383051,
    "bid": "FAcsnmAnp",
    "article_url": "",
    "pics": "",
    "video_url": "",
    "location": "",
    "created_at": "2017-12-18",
    "source": "皮皮时光机",
    "attitudes_count": 2,
    "comments_count": 0,
    "reposts_count": 1,
    "topics": "",
    "at_users": "",
    "history_date": "1942年12月18日",
    "type": 0
}