{
    "text": "1938年6月21日讯：闻当局考虑设立乡镇民意机关 ",
    "user_id": 2896390104,
    "screen_name": "抗战直播",
    "id": 3591706446171542,
    "bid": "zCtHCpTv0",
    "article_url": "",
    "pics": "https://ww3.sinaimg.cn/large/aca367d8jw1e5vywcdkf3j207n09zq3o.jpg",
    "video_url": "",
    "location": "",
    "created_at": "2013-06-21",
    "source": "皮皮时光机",
    "attitudes_count": 0,
    "comments_count": 0,
    "reposts_count": 0,
    "topics": "",
    "at_users": "",
    "history_date": "1938年06月21日",
    "type": 0
}