{
    "text": "#参战装备#日本海军“旗风”号驱逐舰（下）：全面侵华战争爆发后，“旗风”号与同级的三艘驱逐舰”松风“、”朝风“及”春风“号共同组成第五驱逐队，隶属于日本海军遣华舰队第五水雷战队，驻扎华北沿海。太平洋战争爆发后，该舰主要为船团护航。1945年1月15日，在台湾高雄外海被美国海军舰载机击沉。 ",
    "user_id": 2896390104,
    "screen_name": "抗战直播",
    "id": 3987658201684226,
    "bid": "DAMoc748W",
    "article_url": "",
    "pics": "https://ww2.sinaimg.cn/large/aca367d8jw1f4z5bvnfrtj20m807jjtl.jpg",
    "video_url": "",
    "location": "",
    "created_at": "2016-06-18",
    "source": "皮皮时光机",
    "attitudes_count": 8,
    "comments_count": 0,
    "reposts_count": 4,
    "topics": "参战装备",
    "at_users": "",
    "history_date": "1941年06月18日",
    "type": 0
}