{
    "text": "#贾庄战斗#1945年6月17日讯：日军200余人伪军500余人，大车数十辆，到馆陶贾庄、和尚寨一带抢粮。我冀鲁豫军区第3军分区部队在司令员张维翰、副司令员亲自指挥23团2000余人与敌激战。毙敌180余人，俘日军10人，歼伪军400余人，予敌以致命打击。此战也是馆陶境内对敌最后一次大的战斗。 ",
    "user_id": 2896390104,
    "screen_name": "抗战直播",
    "id": 4516729466321753,
    "bid": "J71d0qwzL",
    "article_url": "",
    "pics": "",
    "video_url": "",
    "location": "",
    "created_at": "2020-06-17",
    "source": "皮皮时光机",
    "attitudes_count": 13,
    "comments_count": 1,
    "reposts_count": 1,
    "topics": "贾庄战斗",
    "at_users": "",
    "history_date": "1945年06月17日",
    "type": 0
}