{
    "text": "1938年10月26日讯：津浦路敌军车迭遭炸毁 ",
    "user_id": 2896390104,
    "screen_name": "抗战直播",
    "id": 3637714593305048,
    "bid": "AfP7ZdRNe",
    "article_url": "",
    "pics": "https://ww4.sinaimg.cn/large/aca367d8jw1e9yqv0dkr4j20eg074dhp.jpg",
    "video_url": "",
    "location": "",
    "created_at": "2013-10-26",
    "source": "皮皮时光机",
    "attitudes_count": 0,
    "comments_count": 0,
    "reposts_count": 0,
    "topics": "",
    "at_users": "",
    "history_date": "1938年10月26日",
    "type": 0
}