{
    "text": "1941年5月1日讯：新四军皖南突围部队与无为游击纵队、第3支队挺进团合编为新四军第7师，张鼎丞任师长（未到职），曾希圣任政治委员，李志高任参谋长，辖第19旅及挺进团。该师活动于皖江地区。第5师第14旅一部与第3支队挺进团在安徽宿松县陈汉沟会师，与第7师的联系已打通。 ",
    "user_id": 2896390104,
    "screen_name": "抗战直播",
    "id": 3970233239282118,
    "bid": "Dtt5pCWHA",
    "article_url": "",
    "pics": "",
    "video_url": "",
    "location": "",
    "created_at": "2016-05-01",
    "source": "皮皮时光机",
    "attitudes_count": 12,
    "comments_count": 1,
    "reposts_count": 2,
    "topics": "",
    "at_users": "",
    "history_date": "1941年05月01日",
    "type": 0
}