{
    "text": "#半塔集战斗#1940年3月27日讯：新四军东返主力先头部队已达到半塔西南四十华里之张山集。韩德勤部队见新四军东西两路援军逼近，惧遭覆灭，全线动摇，仓惶后撤。前来增援的常备10旅2个团，也在三河北岸停滞不前。 ",
    "user_id": 2896390104,
    "screen_name": "抗战直播",
    "id": 3824916065687010,
    "bid": "CasbcnRrY",
    "article_url": "",
    "pics": "",
    "video_url": "",
    "location": "",
    "created_at": "2015-03-27",
    "source": "皮皮时光机",
    "attitudes_count": 1,
    "comments_count": 1,
    "reposts_count": 1,
    "topics": "半塔集战斗",
    "at_users": "",
    "history_date": "1940年03月27日",
    "type": 0
}