{
    "text": "1931年11月21日《申报》：东京讯，日将强占平津一带，借口地方形势尚未平静，为保护居留民之不安起见，决派佐世保之嵯峨、出云、八云（号）等舰，以及第27驱逐舰队开往天津，各舰已准备完竣，升火待发。（20日电通电） ",
    "user_id": 2896390104,
    "screen_name": "抗战直播",
    "id": 4573669353851612,
    "bid": "JuUtxg9YM",
    "article_url": "",
    "pics": "",
    "video_url": "",
    "location": "",
    "created_at": "2020-11-21",
    "source": "皮皮时光机",
    "attitudes_count": 65,
    "comments_count": 2,
    "reposts_count": 4,
    "topics": "",
    "at_users": "",
    "history_date": "1931年11月21日",
    "type": 1
}