{
    "text": "#参战装备#日本海军“友鹤”号水雷艇(上)：为千鸟级水雷艇的第3号舰，二战日本海军将600吨以下其他国家称为鱼雷艇的小型高速艇归划归水雷艇。该艇于1934年2月在舞鹤海军工厂竣工，排水量535吨，最高航速30节，舰 员120人。武备为3门127毫米炮，533毫米鱼雷发射管4具，深弹48枚，战斗力接近二等驱逐舰。 ",
    "user_id": 2896390104,
    "screen_name": "抗战直播",
    "id": 3862634267276372,
    "bid": "Cqhp0uwUQ",
    "article_url": "",
    "pics": "https://ww4.sinaimg.cn/large/aca367d8jw1etwaj29o40j20dc09v40i.jpg",
    "video_url": "",
    "location": "",
    "created_at": "2015-07-09",
    "source": "皮皮时光机",
    "attitudes_count": 2,
    "comments_count": 2,
    "reposts_count": 1,
    "topics": "参战装备",
    "at_users": "",
    "history_date": "1940年07月09日",
    "type": 0
}