{
    "text": "1941年12月5日讯：周恩来接刘为章来函。函称何文鼎新二十六师仍驻原地未 动，要求延安撤兵，恢复原来态势。周恩来将刘信电转毛泽东后，毛泽东嘱周恩来答复刘:只要何师不再南下，我军当即退回原防。 ",
    "user_id": 2896390104,
    "screen_name": "抗战直播",
    "id": 4049279121403999,
    "bid": "EkFYs5Tf9",
    "article_url": "",
    "pics": "",
    "video_url": "",
    "location": "",
    "created_at": "2016-12-05",
    "source": "皮皮时光机",
    "attitudes_count": 3,
    "comments_count": 0,
    "reposts_count": 1,
    "topics": "",
    "at_users": "",
    "history_date": "1941年12月05日",
    "type": 0
}