{
    "text": "1941年4月10日讯：襄河东岸日军三路北犯大洪山，一路2000余人犯长寿店，第 五战区一部与敌激战后，敌续窜丰乐河，一路至周家集，一路至王家岭、 邵家店。 ",
    "user_id": 2896390104,
    "screen_name": "抗战直播",
    "id": 3962759068363428,
    "bid": "DqkEiz5I0",
    "article_url": "",
    "pics": "",
    "video_url": "",
    "location": "",
    "created_at": "2016-04-10",
    "source": "皮皮时光机",
    "attitudes_count": 10,
    "comments_count": 2,
    "reposts_count": 2,
    "topics": "",
    "at_users": "",
    "history_date": "1941年04月10日",
    "type": 0
}