{
    "text": "#抗战装备#广东海军“仲元”号炮艇：广东军事厅造船科科长伍景英设计，1928年10月在香港太古造船厂完工，排水量60吨，武备为1门37毫米机炮，4门1磅机炮，4挺6.5毫米机枪和2门迫击炮。该舰名为纪念被陈炯明刺殺的邓铿(字仲元)。1938年10月与“仲恺”号参加三水滘口水战，同年12月被日机炸沉于广东西江。 ",
    "user_id": 2896390104,
    "screen_name": "抗战直播",
    "id": 3934387144176989,
    "bid": "Deqz8hwCN",
    "article_url": "",
    "pics": "https://ww2.sinaimg.cn/large/aca367d8jw1f0978ex25jj20go090ab3.jpg",
    "video_url": "",
    "location": "",
    "created_at": "2016-01-23",
    "source": "皮皮时光机",
    "attitudes_count": 7,
    "comments_count": 4,
    "reposts_count": 7,
    "topics": "抗战装备",
    "at_users": "",
    "history_date": "1941年01月23日",
    "type": 0
}