{
    "text": "1944年12月25日讯：中国西部科学博物馆在四川北碚开馆典礼暨中国科学社三十周年在北碚区纪念会联合大会举行。主席翁文灏致词，中国科学社社长任鸿隽解释西部科学院的工作。科学研究者300余人出席。 ",
    "user_id": 2896390104,
    "screen_name": "抗战直播",
    "id": 4453477621591686,
    "bid": "Imrce6G4m",
    "article_url": "",
    "pics": "",
    "video_url": "",
    "location": "",
    "created_at": "2019-12-25",
    "source": "皮皮时光机",
    "attitudes_count": 3,
    "comments_count": 0,
    "reposts_count": 0,
    "topics": "",
    "at_users": "",
    "history_date": "1944年12月25日",
    "type": 0
}