{
    "text": "1942年6月4日讯：中共冀中区委和八路军冀中军区除留部分地方武装就地坚持 反“清剿”斗争外，领导机关和主力部队迅速转向邻区。（至7月初，冀中 区委和军区及主力部队一部转移到冀鲁豫边区抗日裉据地;另•-部转 移到山东抗日根据地冀鲁边区。冀中军民在两个月的反“扫荡”中，共  ... ",
    "user_id": 2896390104,
    "screen_name": "抗战直播",
    "id": 4115037306428241,
    "bid": "F6jbIqYhj",
    "article_url": "",
    "pics": "https://wx4.sinaimg.cn/large/aca367d8ly1fg9im960hij20c80dv3ys.jpg",
    "video_url": "",
    "location": "",
    "created_at": "2017-06-04",
    "source": "皮皮时光机",
    "attitudes_count": 2,
    "comments_count": 0,
    "reposts_count": 2,
    "topics": "",
    "at_users": "",
    "history_date": "1942年06月04日",
    "type": 0
}