{
    "text": "1940年5月5日讯：纪念五五，国府颁发勋章 ",
    "user_id": 2896390104,
    "screen_name": "抗战直播",
    "id": 3839248845260895,
    "bid": "Cgt2Am4B9",
    "article_url": "",
    "pics": "https://ww1.sinaimg.cn/large/aca367d8jw1ertor1awzcj20e10e0ta4.jpg",
    "video_url": "",
    "location": "",
    "created_at": "2015-05-05",
    "source": "皮皮时光机",
    "attitudes_count": 0,
    "comments_count": 0,
    "reposts_count": 1,
    "topics": "",
    "at_users": "",
    "history_date": "1940年05月05日",
    "type": 0
}