{
    "text": "1938年9月21日讯：国联决定引用盟约第十七条，对付日本，援助中国。此举将招致美中立以对日 ",
    "user_id": 2896390104,
    "screen_name": "抗战直播",
    "id": 3625076350020963,
    "bid": "AawlJ05s7",
    "article_url": "",
    "pics": "https://ww3.sinaimg.cn/large/aca367d8jw1e8ufdn8p0ej20a92bugt6.jpg",
    "video_url": "",
    "location": "",
    "created_at": "2013-09-21",
    "source": "皮皮时光机",
    "attitudes_count": 1,
    "comments_count": 0,
    "reposts_count": 0,
    "topics": "",
    "at_users": "",
    "history_date": "1938年09月21日",
    "type": 0
}