{
    "text": "1941年8月22日讯：英称不考虑解冻对日资金 ",
    "user_id": 2896390104,
    "screen_name": "抗战直播",
    "id": 4011394494209504,
    "bid": "E4MqdhF5e",
    "article_url": "",
    "pics": "https://ww1.sinaimg.cn/large/aca367d8jw1f72vel9p87j202u0vv76b.jpg",
    "video_url": "",
    "location": "",
    "created_at": "2016-08-22",
    "source": "皮皮时光机",
    "attitudes_count": 4,
    "comments_count": 0,
    "reposts_count": 1,
    "topics": "",
    "at_users": "",
    "history_date": "1941年08月22日",
    "type": 0
}