{
    "text": "1943年12月2日讯：日军第三师团反攻德山。周庆祥师官兵坚守德山，死伤三分之一，处在兵单力薄、孤立无援、弹粮不继境地。半夜以后，日第三师团与第六十八师团清水旅团之一部（泽多大队）相配合，又对据守德山附近阵地的第三师1500人发起强攻。 ",
    "user_id": 2896390104,
    "screen_name": "抗战直播",
    "id": 4312848526273141,
    "bid": "H5ofqqjVH",
    "article_url": "",
    "pics": "",
    "video_url": "",
    "location": "",
    "created_at": "2018-12-02",
    "source": "皮皮时光机",
    "attitudes_count": 2,
    "comments_count": 0,
    "reposts_count": 0,
    "topics": "",
    "at_users": "",
    "history_date": "1943年12月02日",
    "type": 0
}