{
    "text": "1943年9月8日讯：彭德怀电告毛泽东，工作布置已毕，他将与刘伯承10日从八路军总部启程赴延安。彭德怀抵达延安后，一直在延安协助毛泽东、朱德指挥华北敌后抗战。 ",
    "user_id": 2896390104,
    "screen_name": "抗战直播",
    "id": 4281886953698879,
    "bid": "GymfJfwfl",
    "article_url": "",
    "pics": "",
    "video_url": "",
    "location": "",
    "created_at": "2018-09-08",
    "source": "皮皮时光机",
    "attitudes_count": 10,
    "comments_count": 2,
    "reposts_count": 1,
    "topics": "",
    "at_users": "",
    "history_date": "1943年09月08日",
    "type": 0
}