{
    "text": "1944年10月9日讯：军事委员会政治部发表《告全国青年文告》，号召知识青年从军，提出“丢下书本，背上枪炮！”“丢下职业，跨入军营！”“出了学校，走上战场！”“一寸山河一寸血，十万青年十万军”等口号。 ",
    "user_id": 2896390104,
    "screen_name": "抗战直播",
    "id": 4425468151794169,
    "bid": "IaGxF7wKd",
    "article_url": "",
    "pics": "",
    "video_url": "",
    "location": "",
    "created_at": "2019-10-09",
    "source": "皮皮时光机",
    "attitudes_count": 8,
    "comments_count": 3,
    "reposts_count": 2,
    "topics": "",
    "at_users": "",
    "history_date": "1944年10月09日",
    "type": 0
}