{
    "text": "1937年8月9日讯：美国国务卿赫尔7月16日重申，美国外交政策已促进世界和平为基础，迄今已有英法、北欧南美等四十余国予以相应，昨日苏联亦复信美方，表示愿为和平尽力，希望能够国际携手，挽救危机。 ",
    "user_id": 2896390104,
    "screen_name": "抗战直播",
    "id": 3477023266097227,
    "bid": "ywjJ4pAan",
    "article_url": "",
    "pics": "",
    "video_url": "",
    "location": "",
    "created_at": "2012-08-09",
    "source": "皮皮时光机",
    "attitudes_count": 4,
    "comments_count": 1,
    "reposts_count": 1,
    "topics": "",
    "at_users": "",
    "history_date": "1937年08月09日",
    "type": 0
}