{
    "text": "1940年3月9日讯：日本首相米内在参议院发表谈话，重申日本政府处理中国事变之方针，在于建设新秩序以保持东亚永久安定，更进而贡献于世界之和平，并称，以汪精卫为中心之中央政府行将成立。帝国决定从速承认，并予以全面援助。他要求日本国民应依据既定方针，举国一致，誓向事变解决一途迈进。 ",
    "user_id": 2896390104,
    "screen_name": "抗战直播",
    "id": 3818589234690686,
    "bid": "C7NADjGge",
    "article_url": "",
    "pics": "",
    "video_url": "",
    "location": "",
    "created_at": "2015-03-09",
    "source": "皮皮时光机",
    "attitudes_count": 3,
    "comments_count": 0,
    "reposts_count": 2,
    "topics": "",
    "at_users": "",
    "history_date": "1940年03月09日",
    "type": 0
}