{
    "text": "1943年11月4日讯：常德方面，因第99军的第92师不战而退，日军左翼占领三仙湖，进抵洞庭洞北岸。而右翼在第3师团后方跟进的佐佐木支队从第13、第3师团之间加入战斗。当日中午攻占公安。 ",
    "user_id": 2896390104,
    "screen_name": "抗战直播",
    "id": 4302588381937093,
    "bid": "H15kO87Vr",
    "article_url": "",
    "pics": "",
    "video_url": "",
    "location": "",
    "created_at": "2018-11-04",
    "source": "皮皮时光机",
    "attitudes_count": 5,
    "comments_count": 1,
    "reposts_count": 2,
    "topics": "",
    "at_users": "",
    "history_date": "1943年11月04日",
    "type": 0
}