{
    "text": "#参战装备#日本海军“早霜”号驱逐舰（四）：日军“不知火”和“藤波”号曾试图救援该舰，但反被美军飞机空袭击沉。1944年10月27日，“早霜”号撤退到民都洛岛南方时再次遭到美军舰载机攻击，被一发航空鱼雷及多枚近失弹命中沉没，此时距离该舰竣工才只有8个月。幸存舰员被“那智”号侦察机发现得救。 ",
    "user_id": 2896390104,
    "screen_name": "抗战直播",
    "id": 4315981629039745,
    "bid": "H6HKOBVEl",
    "article_url": "",
    "pics": "https://wx3.sinaimg.cn/large/aca367d8ly1fy2kr6m8dhj20xc0q2gxg.jpg",
    "video_url": "",
    "location": "",
    "created_at": "2018-12-11",
    "source": "皮皮时光机",
    "attitudes_count": 1,
    "comments_count": 0,
    "reposts_count": 0,
    "topics": "参战装备",
    "at_users": "",
    "history_date": "1943年12月11日",
    "type": 0
}