{
    "text": "1938年12月13日：美对日经济制裁已如箭在弦上，其严厉程度将超过对德国的制裁 ",
    "user_id": 2896390104,
    "screen_name": "抗战直播",
    "id": 3655031418811529,
    "bid": "An5ClAYhr",
    "article_url": "",
    "pics": "https://ww2.sinaimg.cn/large/aca367d8jw1ebhzo5sby0j20cs0xmdnc.jpg",
    "video_url": "",
    "location": "",
    "created_at": "2013-12-13",
    "source": "皮皮时光机",
    "attitudes_count": 1,
    "comments_count": 0,
    "reposts_count": 0,
    "topics": "",
    "at_users": "",
    "history_date": "1938年12月13日",
    "type": 0
}