{
    "text": "1938年5月21日讯：日本大本营根据双方基本战略态势，判定会战已经基本结束，要求日军的进攻大略停止于兰封、商丘、永城、蒙城联结线以东。但是第1军不甘心只做配角，独断决定14师团西进，攻占开封。“西逃”日军集结后攻击兰封，指向开封。 ",
    "user_id": 2896390104,
    "screen_name": "抗战直播",
    "id": 3580379305131919,
    "bid": "zxJ22lx2T",
    "article_url": "",
    "pics": "https://ww1.sinaimg.cn/large/aca367d8jw1e4vtzsic1dj209b09ugmc.jpg",
    "video_url": "",
    "location": "",
    "created_at": "2013-05-21",
    "source": "皮皮时光机",
    "attitudes_count": 0,
    "comments_count": 0,
    "reposts_count": 5,
    "topics": "",
    "at_users": "",
    "history_date": "1938年05月21日",
    "type": 0
}