{
    "text": "1944年2月10日讯：晋察冀边区党政军民领导机关联合召开第一届群英大会。程子华、刘澜涛、宋邵文等出席。大会奖励了104名战斗英雄和模范工作者，并决定授予邓世军“晋察冀边区子弟兵战斗英雄”、李勇“晋察冀边区爆炸英雄”、戎冠秀“北岳区拥军模范——子弟兵母亲”等光荣称号。 ",
    "user_id": 2896390104,
    "screen_name": "抗战直播",
    "id": 4338072185490292,
    "bid": "HfYqKn2h6",
    "article_url": "",
    "pics": "",
    "video_url": "",
    "location": "",
    "created_at": "2019-02-10",
    "source": "皮皮时光机",
    "attitudes_count": 3,
    "comments_count": 0,
    "reposts_count": 0,
    "topics": "",
    "at_users": "",
    "history_date": "1944年02月10日",
    "type": 0
}