{
    "text": "1944年2月10日讯：内政部政务次长张维翰结束对东南及西南各省政务视察返渝，是日对中央社记者发表谈话，认为“县各级民意机关不难于成立，而要在如何切实指导，俾能熟谙《民权初步》及四权行使练习。否则，虽然成立也不过徒具形式而已”。 ",
    "user_id": 2896390104,
    "screen_name": "抗战直播",
    "id": 4338193128088731,
    "bid": "Hg1zOxWfp",
    "article_url": "",
    "pics": "",
    "video_url": "",
    "location": "",
    "created_at": "2019-02-10",
    "source": "皮皮时光机",
    "attitudes_count": 2,
    "comments_count": 0,
    "reposts_count": 0,
    "topics": "",
    "at_users": "",
    "history_date": "1944年02月10日",
    "type": 0
}