{
    "text": "#参战装备#日制八九式旋回航空机枪，1929年日本陆军航空队装备，以2挺7.7毫米仿路易斯航空机枪并联，横向采用类似大正11式机枪的漏斗供弹机构，配以2具各容纳9个5发弹夹的扇形弹鼓。其射速高达到每分钟1400发，但故障率较高，且装满弹鼓重量达32公斤。该枪普遍装备抗战初期日军陆航的轰炸机和侦察机。 ",
    "user_id": 2896390104,
    "screen_name": "抗战直播",
    "id": 3631430683172585,
    "bid": "AdbEEdjkJ",
    "article_url": "",
    "pics": "https://ww4.sinaimg.cn/large/aca367d8jw1e9ep5wpx8fj20go0q60uh.jpg",
    "video_url": "",
    "location": "",
    "created_at": "2013-10-09",
    "source": "皮皮时光机",
    "attitudes_count": 0,
    "comments_count": 5,
    "reposts_count": 4,
    "topics": "参战装备",
    "at_users": "",
    "history_date": "1938年10月09日",
    "type": 0
}