{
    "text": "#上高会战#1941年2月24日讯：日军第11军决定乘第20旅团已经调来、第33师团尚未调走的机会组织一次进攻作战。计划以三路部队分进合击，压迫、包围中国第19集团军主力于上高地区。日军战史把这次作战称为“锦江作战”或“鄱阳作战”。 ",
    "user_id": 2896390104,
    "screen_name": "抗战直播",
    "id": 3945953377804876,
    "bid": "DjhslwKp6",
    "article_url": "",
    "pics": "",
    "video_url": "",
    "location": "",
    "created_at": "2016-02-24",
    "source": "皮皮时光机",
    "attitudes_count": 4,
    "comments_count": 8,
    "reposts_count": 3,
    "topics": "上高会战",
    "at_users": "",
    "history_date": "1941年02月24日",
    "type": 0
}