{
    "text": "1940年11月22日讯：美加强援英，空中堡垒将率先交付二十架 ",
    "user_id": 2896390104,
    "screen_name": "抗战直播",
    "id": 3912075115719732,
    "bid": "D547ZnZXK",
    "article_url": "",
    "pics": "https://ww2.sinaimg.cn/large/aca367d8jw1eya0qdapqtj20bj0kkn0w.jpg",
    "video_url": "",
    "location": "",
    "created_at": "2015-11-22",
    "source": "皮皮时光机",
    "attitudes_count": 6,
    "comments_count": 0,
    "reposts_count": 1,
    "topics": "",
    "at_users": "",
    "history_date": "1940年11月22日",
    "type": 0
}