{
    "text": "#灯明寺战斗# 1939年1月23日讯：我八路军挺进纵队曾国华支队雪夜急行军3个多小时，于今日凌晨2点钟袭击了灯明寺，重创日军留守的一个中队，敌完全丧失战力，返回救援的日军主力亦遭我军伏击，击毁卡车一辆，此战两处日军被毙伤近百人。 ",
    "user_id": 2896390104,
    "screen_name": "抗战直播",
    "id": 3669828705786713,
    "bid": "AtiyWoho5",
    "article_url": "",
    "pics": "",
    "video_url": "",
    "location": "",
    "created_at": "2014-01-23",
    "source": "皮皮时光机",
    "attitudes_count": 2,
    "comments_count": 5,
    "reposts_count": 1,
    "topics": "灯明寺战斗",
    "at_users": "",
    "history_date": "1939年01月23日",
    "type": 0
}