{
    "text": "1940年9月20日新华日报：外汇与物价 ",
    "user_id": 2896390104,
    "screen_name": "抗战直播",
    "id": 3889258391513391,
    "bid": "CBs196lHx",
    "article_url": "",
    "pics": "https://ww2.sinaimg.cn/large/aca367d8jw1ew989ndf3tj211s0hgq97.jpg",
    "video_url": "",
    "location": "",
    "created_at": "2015-09-20",
    "source": "皮皮时光机",
    "attitudes_count": 1,
    "comments_count": 1,
    "reposts_count": 1,
    "topics": "",
    "at_users": "",
    "history_date": "1940年09月20日",
    "type": 0
}