{
    "text": "1944年10月17日中央社讯：伪华北政务委员会设立献铜献木委员会，将北平故宫明代铜缸66只，铜炮三尊，准备献敌。另以天坛、先农坛、西山等处古木编号砍伐备献。 ",
    "user_id": 2896390104,
    "screen_name": "抗战直播",
    "id": 4428518157192102,
    "bid": "IbXT1uaZE",
    "article_url": "",
    "pics": "",
    "video_url": "",
    "location": "",
    "created_at": "2019-10-17",
    "source": "皮皮时光机",
    "attitudes_count": 4,
    "comments_count": 1,
    "reposts_count": 0,
    "topics": "",
    "at_users": "",
    "history_date": "1944年10月17日",
    "type": 0
}