{
    "text": "1944年1月14日讯：国民参政会驻委会在重庆举行会议，与会者有张伯苓、孔庚、黄炎培、李中襄、董必武、许德珩、邵力子等20余人。农林部长沈鸿烈报告农林行政工作及1944年度施政计划。提出工作要点为充裕军用、安定民生，以适应战时需要，并准备战后复员。通过《调整经济机构，制定战后建设纲领》等案。 ",
    "user_id": 2896390104,
    "screen_name": "抗战直播",
    "id": 4328317639393391,
    "bid": "HbSFBDpEj",
    "article_url": "",
    "pics": "",
    "video_url": "",
    "location": "",
    "created_at": "2019-01-14",
    "source": "皮皮时光机",
    "attitudes_count": 2,
    "comments_count": 0,
    "reposts_count": 0,
    "topics": "",
    "at_users": "",
    "history_date": "1944年01月14日",
    "type": 0
}