{
    "text": "1938年4月23日讯：长治沁县收复 ",
    "user_id": 2896390104,
    "screen_name": "抗战直播",
    "id": 3570325566519524,
    "bid": "ztvukrm1C",
    "article_url": "",
    "pics": "https://ww1.sinaimg.cn/large/aca367d8jw1e3zrc6rvvmj20lw0eo781.jpg",
    "video_url": "",
    "location": "",
    "created_at": "2013-04-23",
    "source": "皮皮时光机",
    "attitudes_count": 0,
    "comments_count": 0,
    "reposts_count": 1,
    "topics": "",
    "at_users": "",
    "history_date": "1938年04月23日",
    "type": 0
}