{
    "text": "1931年12月3日讯：旅欧华侨救国总会电《大公报》转全国同胞，略谓国联助日亡我，施肇基又放弃日兵限期撤退案，政府已与日直接交涉，接受亡国条件，划锦州中立区，开共管恶例，此种卖国外交决不能接受。 ",
    "user_id": 2896390104,
    "screen_name": "抗战直播",
    "id": 4578161424345997,
    "bid": "JwNkOieAJ",
    "article_url": "",
    "pics": "",
    "video_url": "",
    "location": "",
    "created_at": "2020-12-03",
    "source": "皮皮时光机",
    "attitudes_count": 77,
    "comments_count": 1,
    "reposts_count": 0,
    "topics": "",
    "at_users": "",
    "history_date": "1931年12月03日",
    "type": 1
}