{
    "text": "（接上条）规定：一、日本军事机关与中国军警各机关应保持紧密 联系,共同负责所辖区域内的治安警卫;二、日本各军司令官、各兵团 长、各地区警备队长及各地宪兵队长，有权指挥所辖区域内中国军警指 挥官及其下属指挥官。 ",
    "user_id": 2896390104,
    "screen_name": "抗战直播",
    "id": 3857276434076843,
    "bid": "Co21lh6zx",
    "article_url": "",
    "pics": "",
    "video_url": "",
    "location": "",
    "created_at": "2015-06-24",
    "source": "皮皮时光机",
    "attitudes_count": 0,
    "comments_count": 0,
    "reposts_count": 1,
    "topics": "",
    "at_users": "",
    "history_date": "1940年06月24日",
    "type": 0
}