{
    "text": "1939年3月23日讯：国民党中常会通过《军队党务整理办法》19条，确定陆军党部工作的指导考核由中央组织部掌理，陆军训练宣传工作的指导考核由军委政治部掌理，军队党部委员名额及人选由组 织部商同政治部呈请总裁决定。 ",
    "user_id": 2896390104,
    "screen_name": "抗战直播",
    "id": 3691375868910599,
    "bid": "ACl6qBo3l",
    "article_url": "",
    "pics": "",
    "video_url": "",
    "location": "",
    "created_at": "2014-03-23",
    "source": "皮皮时光机",
    "attitudes_count": 2,
    "comments_count": 0,
    "reposts_count": 0,
    "topics": "",
    "at_users": "",
    "history_date": "1939年03月23日",
    "type": 0
}