{
    "text": "#抗战装备#中国装甲列车(下)：一·二八淞沪抗战中参战的部分中国装甲列车被汉奸指示位置而被日机炸毁，剩余的在日军大幅增兵后主动后撤。比如北平号后来曾出现在济南。尽管中国装甲列车部队在淞沪前线参战时间不长，而且暴露了其必须依托铁路线才能机动的弊端，但其英勇战斗的表现仍然可圈可点。 ",
    "user_id": 2896390104,
    "screen_name": "抗战直播",
    "id": 3666582347869976,
    "bid": "ArW6Sx1l6",
    "article_url": "",
    "pics": "https://ww3.sinaimg.cn/large/aca367d8jw1eciu9z4dw2j20cs0c3did.jpg",
    "video_url": "",
    "location": "",
    "created_at": "2014-01-14",
    "source": "皮皮时光机",
    "attitudes_count": 2,
    "comments_count": 0,
    "reposts_count": 3,
    "topics": "抗战装备",
    "at_users": "",
    "history_date": "1939年01月14日",
    "type": 0
}