{
    "text": "1943年7月7日讯：史迪威代表美国总统罗斯福总统在重庆举行授勋典礼，授予蒋介石“最高统帅勋章”，何应钦、商震“司令勋章”，国民政府兵工署署长俞大维、国民政府远征军卫生总视察林可胜“将官勋章”。 ",
    "user_id": 2896390104,
    "screen_name": "抗战直播",
    "id": 4259252794868264,
    "bid": "GoRr1kqso",
    "article_url": "",
    "pics": "",
    "video_url": "",
    "location": "",
    "created_at": "2018-07-07",
    "source": "皮皮时光机",
    "attitudes_count": 3,
    "comments_count": 0,
    "reposts_count": 1,
    "topics": "",
    "at_users": "",
    "history_date": "1943年07月07日",
    "type": 0
}