{
    "text": "1940年3月4日讯:朱德为驳斥国民党顽固派对八路军的诬蔑，向华北同胞陈述八路军战绩及一贯主张：1.本军在华北抗战已历时三年，作战5000次以上，收复失地数十县，消灭敌寇20余万，缴获之多，冠于全国，人人共知；2.本军为抗日民族统一战线之发起者与坚持者，必抗战到底，驱逐日寇出中国（转下条） ",
    "user_id": 2896390104,
    "screen_name": "抗战直播",
    "id": 3816807490356854,
    "bid": "C73eR1uPI",
    "article_url": "",
    "pics": "",
    "video_url": "",
    "location": "",
    "created_at": "2015-03-04",
    "source": "皮皮时光机",
    "attitudes_count": 1,
    "comments_count": 2,
    "reposts_count": 1,
    "topics": "",
    "at_users": "",
    "history_date": "1940年03月04日",
    "type": 0
}