{
    "text": "1944年11月11日讯：成都四川大学、华西大学、金陵大学、燕京大学等校学生7000余人举行示威游行，声援10月31日成都学生运动，要求民主自由，要求国民党当局惩凶、恤伤、保障人身自由等。学生至四川省府门前，要求面见省主席张群，张群出面允诺学生的要求。 ",
    "user_id": 2896390104,
    "screen_name": "抗战直播",
    "id": 4437517447100068,
    "bid": "IfK00tN3e",
    "article_url": "",
    "pics": "",
    "video_url": "",
    "location": "",
    "created_at": "2019-11-11",
    "source": "皮皮时光机",
    "attitudes_count": 2,
    "comments_count": 0,
    "reposts_count": 0,
    "topics": "",
    "at_users": "",
    "history_date": "1944年11月11日",
    "type": 0
}