{
    "text": "1941年6月4日讯：冀察战区第六十九军军长兼察哈尔省主席毕泽宇率特务团及 骑兵一连约1200余人投降日军。20日，高树勋电孔祥熙称:毕投敌原 因“以其思想不正，重用石逆（即石友三)余孽，群小包围，倒行逆施所 致”。另外，毕曾侵吞公款190余万元，事泄不得已乃走此极端。 ",
    "user_id": 2896390104,
    "screen_name": "抗战直播",
    "id": 3982614816327654,
    "bid": "DyFbHqy6W",
    "article_url": "",
    "pics": "",
    "video_url": "",
    "location": "",
    "created_at": "2016-06-04",
    "source": "皮皮时光机",
    "attitudes_count": 9,
    "comments_count": 3,
    "reposts_count": 3,
    "topics": "",
    "at_users": "",
    "history_date": "1941年06月04日",
    "type": 0
}