{
    "text": "1942年9月：中共冀中党委和军队根据中共中央北方局高干会议关于“成 立以白洋淀、文安洼、大清河一带之苇塘为主的游击根据地，逐渐向外 扩张恢复与开辟”的决定，冀中第八、第十军分区在任丘、安新、文安、大 城和永清等县苇塘水网地带，建立多块游击根据地，这对于在极端艰险 困难关 ... ",
    "user_id": 2896390104,
    "screen_name": "抗战直播",
    "id": 4157708707604333,
    "bid": "FodgyvUex",
    "article_url": "",
    "pics": "https://wx4.sinaimg.cn/large/aca367d8ly1fk1nd07vaij20c809zq2z.jpg",
    "video_url": "",
    "location": "",
    "created_at": "2017-09-30",
    "source": "皮皮时光机",
    "attitudes_count": 3,
    "comments_count": 0,
    "reposts_count": 2,
    "topics": "",
    "at_users": "",
    "history_date": "1942年09月30日",
    "type": 0
}