{
    "text": "1937年8月11日，日军对南口地区展开正式攻击。其主力猛攻南口镇，另以1个大队(坂田支队)向南口镇西侧地区长城线助攻，并以一部在得胜口佯攻。日军步兵在飞机、炮兵、坦克支援下猛攻守军阵地。守军第89师凭有利地形顽强抵抗。 ",
    "user_id": 2896390104,
    "screen_name": "抗战直播",
    "id": 3477808439594438,
    "bid": "ywE9tEfX0",
    "article_url": "",
    "pics": "",
    "video_url": "",
    "location": "",
    "created_at": "2012-08-11",
    "source": "皮皮时光机",
    "attitudes_count": 4,
    "comments_count": 5,
    "reposts_count": 1,
    "topics": "",
    "at_users": "",
    "history_date": "1937年08月11日",
    "type": 0
}