{
    "text": "1938年9月10日讯：沪外白渡桥，日英哨兵发生冲突 ",
    "user_id": 2896390104,
    "screen_name": "抗战直播",
    "id": 3621015089781689,
    "bid": "A8OHiF2Fb",
    "article_url": "",
    "pics": "https://ww3.sinaimg.cn/large/aca367d8jw1e8hgy7cy4ij208p0cpmy8.jpg",
    "video_url": "",
    "location": "",
    "created_at": "2013-09-10",
    "source": "皮皮时光机",
    "attitudes_count": 0,
    "comments_count": 0,
    "reposts_count": 0,
    "topics": "",
    "at_users": "",
    "history_date": "1938年09月10日",
    "type": 0
}