{
    "text": "1943年12月25日讯：国民节约献金救国运动总会会长冯玉祥在成都报告赴各地劝导节约献金情形，谓：自11月8日至是日献金总额已达1400余万元，“各界莫不热烈响应”。 ",
    "user_id": 2896390104,
    "screen_name": "抗战直播",
    "id": 4321175850869731,
    "bid": "H8SSB3EfV",
    "article_url": "",
    "pics": "",
    "video_url": "",
    "location": "",
    "created_at": "2018-12-25",
    "source": "皮皮时光机",
    "attitudes_count": 2,
    "comments_count": 2,
    "reposts_count": 0,
    "topics": "",
    "at_users": "",
    "history_date": "1943年12月25日",
    "type": 0
}