{
    "text": "#滇西反击战#1944年6月7日讯：在我军合围下，北斋公房和冷水丫口的日军处于孤立无援之境，他们储备的粮食弹药也越来越少。日军救援未至，只能以马肉充饥，甚至于发生吃食人肉之事。 ",
    "user_id": 2896390104,
    "screen_name": "抗战直播",
    "id": 4380456453451152,
    "bid": "HxL2tetNK",
    "article_url": "",
    "pics": "",
    "video_url": "",
    "location": "",
    "created_at": "2019-06-07",
    "source": "皮皮时光机",
    "attitudes_count": 7,
    "comments_count": 1,
    "reposts_count": 0,
    "topics": "滇西反击战",
    "at_users": "",
    "history_date": "1944年06月07日",
    "type": 0
}