{
    "text": "1942年6月10日讯：山西河津、稷山之敌千余人，于是日围攻稷山之黄花峪，该地 由第八十三军李如意营守备，敌六次冲锋均被击退，窜人堡内之敌60 余悉数歼灭，激战至次日拂晓，毙伤敌300余，我官兵阵亡150余人。 ",
    "user_id": 2896390104,
    "screen_name": "抗战直播",
    "id": 4117090937797398,
    "bid": "F7aC1wIsu",
    "article_url": "",
    "pics": "",
    "video_url": "",
    "location": "",
    "created_at": "2017-06-10",
    "source": "皮皮时光机",
    "attitudes_count": 2,
    "comments_count": 3,
    "reposts_count": 1,
    "topics": "",
    "at_users": "",
    "history_date": "1942年06月10日",
    "type": 0
}