{
    "text": "1942年12月16日讯：湖北省应城、安陆日伪军600余人，分两路向应城县杨家河、高庙地区“扫荡”，袭击了在杨家河宿营的新四军第5师第13旅第38团，占领了杨家河东北高庙制高点。第38团反复冲杀，肉搏八次，击溃敌军，毙伤日伪军100余人，敌遗尸30余具。我军亦伤亡100余人，团政治委员周庆鸣负伤。 ",
    "user_id": 2896390104,
    "screen_name": "抗战直播",
    "id": 4185506868405556,
    "bid": "FzSqizgFu",
    "article_url": "",
    "pics": "",
    "video_url": "",
    "location": "",
    "created_at": "2017-12-16",
    "source": "皮皮时光机",
    "attitudes_count": 1,
    "comments_count": 0,
    "reposts_count": 1,
    "topics": "",
    "at_users": "",
    "history_date": "1942年12月16日",
    "type": 0
}