{
    "text": "#参战装备#日本海军“敷波”号驱舰逐（六）：1943年1月，在釜山至韦瓦克之间从事陆军部队运输任务，3月参加了俾斯麦海海战。1944年6月8日，参加比亚克海战，轻微受损。8月1日，在新加坡附近触礁，再次受伤，修理后返回战场。1944年9月12日，该舰在香港以南海被美国海军“黑鲈”号潜艇发射鱼雷击沉。 ",
    "user_id": 2896390104,
    "screen_name": "抗战直播",
    "id": 4347147052577517,
    "bid": "HjMvDaOwR",
    "article_url": "",
    "pics": "https://wx3.sinaimg.cn/large/aca367d8ly1g0u01z1ugdj20u00u1x43.jpg",
    "video_url": "",
    "location": "",
    "created_at": "2019-03-07",
    "source": "皮皮时光机",
    "attitudes_count": 2,
    "comments_count": 0,
    "reposts_count": 0,
    "topics": "参战装备",
    "at_users": "",
    "history_date": "1944年03月07日",
    "type": 0
}