{
    "text": "1937年11月1日：上海方面，敌军又到5000援军 ",
    "user_id": 2896390104,
    "screen_name": "抗战直播",
    "id": 3507526757247802,
    "bid": "z39NVupu2",
    "article_url": "",
    "pics": "https://ww4.sinaimg.cn/large/aca367d8jw1dyfeztmz7yj.jpg",
    "video_url": "",
    "location": "",
    "created_at": "2012-11-01",
    "source": "皮皮时光机",
    "attitudes_count": 0,
    "comments_count": 0,
    "reposts_count": 13,
    "topics": "",
    "at_users": "",
    "history_date": "1937年11月01日",
    "type": 0
}