{
    "text": "1944年1月4日讯：东南地区鼠疫严重，以浙江省云和区较为流行，已死亡百余人，疫情有向瓯江流域扩张之势。福建省已蔓延至30余县，已死亡3884人。江西光泽与广东省之大埔亦有疫情。按：此系侵华日军投放细菌所致。 ",
    "user_id": 2896390104,
    "screen_name": "抗战直播",
    "id": 4324761935376823,
    "bid": "HaoaBmyKX",
    "article_url": "",
    "pics": "",
    "video_url": "",
    "location": "",
    "created_at": "2019-01-04",
    "source": "皮皮时光机",
    "attitudes_count": 5,
    "comments_count": 0,
    "reposts_count": 0,
    "topics": "",
    "at_users": "",
    "history_date": "1944年01月04日",
    "type": 0
}