{
    "text": "1944年4月23日讯：社会部召开研究人口政策会议，全国社会学专家陈达、吴文藻、李景汉等10余人出席，会议拟就人口政策、纲领及实施方案内容，呈请当局核定实施。 ",
    "user_id": 2896390104,
    "screen_name": "抗战直播",
    "id": 4364330193516500,
    "bid": "HqZwneKNK",
    "article_url": "",
    "pics": "",
    "video_url": "",
    "location": "",
    "created_at": "2019-04-23",
    "source": "皮皮时光机",
    "attitudes_count": 4,
    "comments_count": 0,
    "reposts_count": 0,
    "topics": "",
    "at_users": "",
    "history_date": "1944年04月23日",
    "type": 0
}