{
    "text": "1931年11月14日《申报》：南京息，第19路军60师129旅刘占雄部，除第1团及2、3两团各一营已过（南）京开赴丹阳常州驻扎外，其余各团营，13（日）相继抵（南）京。随转京沪车开赴苏州常驻一带驻扎。又该路军总指挥部14（日）可抵京。（13日专电） ",
    "user_id": 2896390104,
    "screen_name": "抗战直播",
    "id": 4571140151057983,
    "bid": "JtQGb4ref",
    "article_url": "",
    "pics": "",
    "video_url": "",
    "location": "",
    "created_at": "2020-11-14",
    "source": "皮皮时光机",
    "attitudes_count": 64,
    "comments_count": 0,
    "reposts_count": 0,
    "topics": "",
    "at_users": "",
    "history_date": "1931年11月14日",
    "type": 1
}