{
    "text": "1938年2月22日讯：敌大举捕杀东三省反日志士，仅哈尔滨一日便有500人以上被捕 ",
    "user_id": 2896390104,
    "screen_name": "抗战直播",
    "id": 3548642709544404,
    "bid": "zkppYE2W0",
    "article_url": "",
    "pics": "https://ww4.sinaimg.cn/large/aca367d8jw1e22l3hrrw8j.jpg",
    "video_url": "",
    "location": "",
    "created_at": "2013-02-22",
    "source": "皮皮时光机",
    "attitudes_count": 0,
    "comments_count": 2,
    "reposts_count": 3,
    "topics": "",
    "at_users": "",
    "history_date": "1938年02月22日",
    "type": 0
}