{
    "text": "1942年7月29日讯：新四军军部致电粟裕等，对坚持苏中长期斗争作如下指示:苏 中斗争要准备苦斗一年至两年。苏中工作应以领导武装斗争，进行敌 伪工作、组织领导两面政权、领导民兵为中心。其他任务均应围绕此一 中心进行。部队不应再有主力与地方的区别，保持四个主力团，余均与 地 ... ",
    "user_id": 2896390104,
    "screen_name": "抗战直播",
    "id": 4134817786841757,
    "bid": "FeBLIsHQV",
    "article_url": "",
    "pics": "https://wx2.sinaimg.cn/large/aca367d8ly1fi0mdi55qmj20c8090t8q.jpg",
    "video_url": "",
    "location": "",
    "created_at": "2017-07-29",
    "source": "皮皮时光机",
    "attitudes_count": 3,
    "comments_count": 4,
    "reposts_count": 4,
    "topics": "",
    "at_users": "",
    "history_date": "1942年07月29日",
    "type": 0
}