{
    "text": "1943年8月21日讯：中国卫生教育社召开第三届社员大会，决定组织民族健康运动委员会，由陈果夫任主任。通过“提倡健康运动”、“注重合理营养”等12项工作目标。 ",
    "user_id": 2896390104,
    "screen_name": "抗战直播",
    "id": 4275514992981917,
    "bid": "GvGuncvJr",
    "article_url": "",
    "pics": "",
    "video_url": "",
    "location": "",
    "created_at": "2018-08-21",
    "source": "皮皮时光机",
    "attitudes_count": 1,
    "comments_count": 0,
    "reposts_count": 1,
    "topics": "",
    "at_users": "",
    "history_date": "1943年08月21日",
    "type": 0
}