{
    "text": "1940年10月26日讯：浙东萧山日军于24日向绍兴进犯，是日守军第十六师何干 部、第六十七师莫与硕部弃守，绍兴失陷。（28日，何、莫两部联合反攻， 敌不支，乃向萧山逸去，绍兴失而复得。29日，克复漓渚、河桥等日军 据点。） ",
    "user_id": 2896390104,
    "screen_name": "抗战直播",
    "id": 3902164839320880,
    "bid": "D0UjFD6MM",
    "article_url": "",
    "pics": "",
    "video_url": "",
    "location": "",
    "created_at": "2015-10-26",
    "source": "皮皮时光机",
    "attitudes_count": 11,
    "comments_count": 2,
    "reposts_count": 3,
    "topics": "",
    "at_users": "",
    "history_date": "1940年10月26日",
    "type": 0
}